ProtPlot/__init__.py
ProtPlot/protplot.py
ProtPlot-1.0.0.dist-info/METADATA
ProtPlot-1.0.0.dist-info/WHEEL
ProtPlot-1.0.0.dist-info/top_level.txt
ProtPlot-1.0.0.dist-info/RECORD
